easyllm_utils/__init__.py
easyllm_utils/utils/__init__.py
easyllm_utils/utils/config_utils.py
easyllm_utils/utils/debug_hf_utils.py
easyllm_utils/utils/log_utils.py
easyllm_utils-0.0.2.1.dist-info/LICENSE
easyllm_utils-0.0.2.1.dist-info/METADATA
easyllm_utils-0.0.2.1.dist-info/WHEEL
easyllm_utils-0.0.2.1.dist-info/top_level.txt
easyllm_utils-0.0.2.1.dist-info/RECORD
