Metadata-Version: 2.1
Name: easyllm_utils
Version: 0.0.2.1
Summary: An easy recipes of code for large language model
Home-page: https://github.com/iLampard/llm_recipes
Author: iLampard
Classifier: Programming Language :: Python :: 3.8
Classifier: Programming Language :: Python :: 3.9
Classifier: Programming Language :: Python :: 3.10
License-File: LICENSE
Requires-Dist: torch
Requires-Dist: transformers
Requires-Dist: omegaconf
Requires-Dist: registrable
